MANIFEST.in
README
setup.py
RMseq/RM-seq.pl
RMseq/__init__.py
RMseq/amplicon-effect.py
RMseq/rmseq
RMseq/test_data/R1.fq
RMseq/test_data/R2.fq
RMseq/test_data/RpoB.faa
RMseq/test_data/rpob.fna
rmseq.egg-info/PKG-INFO
rmseq.egg-info/PKG-INFO~
rmseq.egg-info/SOURCES.txt
rmseq.egg-info/dependency_links.txt
rmseq.egg-info/requires.txt
rmseq.egg-info/top_level.txt