Metadata-Version: 1.1
Name: rmseq
Version: 0.0.53b0
Summary: RM-seq is a bioinformatics tool for for assessing resistance mutations from PE short-reads.
Home-page: UNKNOWN
Author: Romain Guerillot, Torsten Seemann, Mark B Schultz
Author-email: romain.guerillot@hotmail.fr
License: AGPL-3.0
Download-URL: https://github.com/rguerillot/RM-seq/zipball/master
Keywords: resistance,mutation
Platform: UNKNOWN
Classifier: Development Status :: 3 - Alpha
Classifier: License :: OSI Approved :: GNU Affero General Public License v3 or later (AGPLv3+)
Classifier: Programming Language :: Python :: 3.5
Classifier: Topic :: Scientific/Engineering :: Bio-Informatics
Classifier: Topic :: Scientific/Engineering :: Medical Science Apps.
Classifier: Intended Audience :: Science/Research
